Metadata-Version: 2.1
Name: switchmultiprocess
Version: 0.0.1
Summary: Multiprocessing module for charging
Home-page: UNKNOWN
Author: Hurrairah Imran
Author-email: hurrairahimran@gmail.com
License: MIT
Keywords: multiprocessing
Platform: UNKNOWN
Classifier: Development Status :: 5 - Production/Stable
Classifier: Intended Audience :: Education
Classifier: Operating System :: Microsoft :: Windows :: Windows 10
Classifier: License :: OSI Approved :: MIT License
Classifier: Programming Language :: Python :: 3
License-File: LICENSE.txt
